<?xml version="1.0" encoding="utf-8"?>
<Topic Id="ca2a2cb9-527a-44b4-bac8-4f62b8404de0" Status="New Topic" CreatedOn="2015-07-30T05:37:59.2087491Z" ModifiedOn="2015-10-28T03:43:48.2252386Z" PageTypeName="" AutoIndex="true" HelpContextIds="" Name="UnderstandingtheProduct" BuildFlags="">
  <Title m="2015-07-30T05:38:19.0036309Z">Understanding the Product</Title>
  <ContentsTitle />
  <Notes></Notes>
  <TopicSections>
    <TopicSection Name="BodyText">
      <Content m="2015-10-28T03:43:48.2252386Z">&lt;P&gt;Spread.Views provides a customizable grid widget for use in browser application. The following section explains some of the underlying concepts for this unique and powerful product.&lt;/P&gt;
&lt;UL&gt;
&lt;LI&gt;&lt;A href="811f0907-c626-404a-a385-2cb45c07282a" style="auto-update-caption: true"&gt;Product Overview&lt;/A&gt; 
&lt;LI&gt;&lt;A href="5a0bc752-f5e2-4e91-a942-846e925b26e8" style="auto-update-caption: true"&gt;Object Inheritance&lt;/A&gt; 
&lt;LI&gt;&lt;A href="b232832a-62a0-4d9b-81b7-b0b19f53134a" style="auto-update-caption: true"&gt;Feature Overview&lt;/A&gt;&amp;nbsp; &lt;/LI&gt;&lt;/UL&gt;
&lt;P&gt;&lt;/P&gt;</Content>
    </TopicSection>
  </TopicSections>
  <TopicLinks />
  <TopicKeywords />
  <PropertyDefinitionValues />
  <ExcludedOtherFiles />
</Topic>