[
    {
        "name" : "_text_repo",
        "type" : "File folder",
        "fileIcon" : "file-folder",
        "extend" : "",
        "dateModified" : "4/1/2015 6:26 PM",
        "sizeAmount": null,
        "sizeMeasure": null,
        "path": "../views_sample4/files/"
    },
    {
        "name" : "_img_repo",
        "type" : "File folder",
        "fileIcon" : "file-folder",
        "extend" : "",
        "dateModified" : "5/30/2015 9:00 AM",
        "sizeAmount": null,
        "sizeMeasure": null,
        "path": "./"
    },
    {
        "name" : "my dream",
        "type" : "File folder",
        "fileIcon" : "file-folder",
        "extend" : "",
        "dateModified" : "4/1/2015 6:26 PM",
        "sizeAmount": null,
        "sizeMeasure": null,
        "path": "./_text_repo/"
    },
    {
        "name" : "try",
        "type" : "TXT",
        "fileIcon" : "TXT",
        "extend" : ".txt",
        "dateModified" : "4/1/2015 6:26 PM",
        "sizeAmount": 560,
        "sizeMeasure": "Bytes",
        "path": "./_text_repo/"
    },
    {
        "name" : "hello",
        "type" : "TXT",
        "fileIcon" : "TXT",
        "extend" : ".txt",
        "dateModified" : "4/1/2015 6:26 PM",
        "sizeAmount": 560,
        "sizeMeasure": "Bytes",
        "path": "./_text_repo/"
    },
    {
        "name" : "what",
        "type" : "TXT",
        "fileIcon" : "TXT",
        "extend" : ".txt",
        "dateModified" : "4/1/2015 6:26 PM",
        "sizeAmount": 560,
        "sizeMeasure": "Bytes",
        "path": "./_text_repo/"
    },
    {
        "name" : "good bye",
        "type" : "TXT",
        "fileIcon" : "TXT",
        "extend" : ".txt",
        "dateModified" : "4/1/2015 6:26 PM",
        "sizeAmount": 560,
        "sizeMeasure": "Bytes",
        "path": "./_text_repo/my dream/"
    },
    {
        "name" : "nice portray",
        "type" : "File folder",
        "fileIcon" : "file-folder",
        "extend" : "",
        "dateModified" : "5/30/2015 9:00 AM",
        "sizeAmount": null,
        "sizeMeasure": null,
        "path": "./_img_repo/"
    },
    {
        "name" : "cans",
        "type" : "BMP",
        "fileIcon" : "BMP",
        "extend" : ".bmp",
        "dateModified" : "5/28/2015 11:30 AM",
        "sizeAmount": 5.66,
        "sizeMeasure": "KB",
        "path": "./_img_repo/"
    },
    {
        "name" : "cats",
        "type" : "BMP",
        "fileIcon" : "BMP",
        "extend" : ".bmp",
        "dateModified" : "5/28/2015 11:30 AM",
        "sizeAmount": 3.25,
        "sizeMeasure": "KB",
        "path": "./_img_repo/"
    },
    {
        "name" : "Odie's cute face",
        "type" : "BMP",
        "fileIcon" : "BMP",
        "extend" : ".bmp",
        "dateModified" : "5/28/2015 11:30 AM",
        "sizeAmount": 12.12,
        "sizeMeasure": "KB",
        "path": "./_img_repo/nice portray/"
    },
    {
        "name" : "a dog",
        "type" : "TXT",
        "fileIcon" : "TXT",
        "extend" : ".txt",
        "dateModified" : "5/28/2015 11:30 AM",
        "sizeAmount": 20,
        "sizeMeasure": "Bytes",
        "path": "./"
    },
    {
        "name" : "once have a dream",
        "type" : "TXT",
        "fileIcon" : "TXT",
        "extend" : ".txt",
        "dateModified" : "5/28/2015 11:30 AM",
        "sizeAmount": 320,
        "sizeMeasure": "Bytes",
        "path": "./"
    },
    {
        "name" : "to have lots of cans",
        "type" : "TXT",
        "fileIcon" : "TXT",
        "extend" : ".txt",
        "dateModified" : "5/28/2015 11:30 AM",
        "sizeAmount": 120,
        "sizeMeasure": "Bytes",
        "path": "./"
    },
    {
        "name" : "without warms inside",
        "type" : "TXT",
        "fileIcon" : "TXT",
        "extend" : ".txt",
        "dateModified" : "5/28/2015 11:30 AM",
        "sizeAmount": 1.23,
        "sizeMeasure": "KB",
        "path": "./"
    },
    {
        "name" : "while the cat is sleeping",
        "type" : "TXT",
        "fileIcon" : "TXT",
        "extend" : ".txt",
        "dateModified" : "5/28/2015 11:30 AM",
        "sizeAmount": 630,
        "sizeMeasure": "Bytes",
        "path": "./"
    },
    {
        "name" : "presumably a feast",
        "type" : "TXT",
        "fileIcon" : "TXT",
        "extend" : ".txt",
        "dateModified" : "5/28/2015 11:30 AM",
        "sizeAmount": 555,
        "sizeMeasure": "Bytes",
        "path": "./"
    },
    {
        "name" : "waits in the end of day",
        "type" : "TXT",
        "fileIcon" : "TXT",
        "extend" : ".txt",
        "dateModified" : "5/28/2015 11:30 AM",
        "sizeAmount": 870,
        "sizeMeasure": "Bytes",
        "path": "./"
    },
    {
        "name" : "cans",
        "type" : "BMP",
        "fileIcon" : "BMP",
        "extend" : ".bmp",
        "dateModified" : "5/28/2015 11:30 AM",
        "sizeAmount": 1.56,
        "sizeMeasure": "KB",
        "path": "./"
    },
    {
        "name" : "cats",
        "type" : "BMP",
        "fileIcon" : "BMP",
        "extend" : ".bmp",
        "dateModified" : "5/28/2015 11:30 AM",
        "sizeAmount": 5.33,
        "sizeMeasure": "KB",
        "path": "./"
    },
    {
        "name" : "show a dream",
        "type" : "HTML",
        "fileIcon" : "HTML",
        "extend" : ".html",
        "dateModified" : "5/29/2015 3:30 PM",
        "sizeAmount": 2.49,
        "sizeMeasure": "KB",
        "path": "./"
    }
]
